clifun.py
clifun-0.0.2.dist-info/LICENSE
clifun-0.0.2.dist-info/WHEEL
clifun-0.0.2.dist-info/METADATA
clifun-0.0.2.dist-info/RECORD
