Metadata-Version: 2.1
Name: clifun
Version: 0.0.2
Summary: Construct a comand line interface based on a function or class
License: MIT
Author: Tom Dimiduk
Author-email: tom@dimiduk.net
Requires-Python: >=3.6.2,<4.0
Classifier: License :: OSI Approved :: MIT License
Classifier: Programming Language :: Python :: 3
Classifier: Programming Language :: Python :: 3.10
Classifier: Programming Language :: Python :: 3.7
Classifier: Programming Language :: Python :: 3.8
Classifier: Programming Language :: Python :: 3.9
